crimson/faiss_indexer/__init__.py
crimson/faiss_indexer/retriever.py
crimson_faiss_indexer-0.1.0.dist-info/LICENSE
crimson_faiss_indexer-0.1.0.dist-info/METADATA
crimson_faiss_indexer-0.1.0.dist-info/WHEEL
crimson_faiss_indexer-0.1.0.dist-info/top_level.txt
crimson_faiss_indexer-0.1.0.dist-info/RECORD
